gpt_oss/__init__.py
gpt_oss/chat.py
gpt_oss/generate.py
gpt_oss/tokenizer.py
gpt_oss/evals/__init__.py
gpt_oss/evals/__main__.py
gpt_oss/evals/abcd_grader.py
gpt_oss/evals/aime_eval.py
gpt_oss/evals/basic_eval.py
gpt_oss/evals/chat_completions_sampler.py
gpt_oss/evals/gpqa_eval.py
gpt_oss/evals/healthbench_eval.py
gpt_oss/evals/report.py
gpt_oss/evals/responses_sampler.py
gpt_oss/evals/types.py
gpt_oss/metal/__init__.py
gpt_oss/metal/examples/chat.py
gpt_oss/metal/examples/generate.py
gpt_oss/metal/scripts/create-local-model.py
gpt_oss/responses_api/__init__.py
gpt_oss/responses_api/api_server.py
gpt_oss/responses_api/events.py
gpt_oss/responses_api/serve.py
gpt_oss/responses_api/types.py
gpt_oss/responses_api/utils.py
gpt_oss/responses_api/inference/__init__.py
gpt_oss/responses_api/inference/metal.py
gpt_oss/responses_api/inference/ollama.py
gpt_oss/responses_api/inference/stub.py
gpt_oss/responses_api/inference/transformers.py
gpt_oss/responses_api/inference/triton.py
gpt_oss/responses_api/inference/vllm.py
gpt_oss/tools/__init__.py
gpt_oss/tools/apply_patch.py
gpt_oss/tools/tool.py
gpt_oss/tools/python_docker/docker_tool.py
gpt_oss/tools/simple_browser/__init__.py
gpt_oss/tools/simple_browser/backend.py
gpt_oss/tools/simple_browser/page_contents.py
gpt_oss/tools/simple_browser/simple_browser_tool.py
gpt_oss/torch/__init__.py
gpt_oss/torch/model.py
gpt_oss/torch/utils.py
gpt_oss/torch/weights.py
gpt_oss/triton/__init__.py
gpt_oss/triton/attention.py
gpt_oss/triton/model.py
gpt_oss/triton/moe.py
gpt_oss/vllm/token_generator.py
gpt_oss-0.0.8.dist-info/licenses/LICENSE
gpt_oss-0.0.8.dist-info/METADATA
gpt_oss-0.0.8.dist-info/WHEEL
gpt_oss-0.0.8.dist-info/top_level.txt
gpt_oss-0.0.8.dist-info/RECORD
