Metadata-Version: 2.4
Name: gpt-oss
Version: 0.0.8
Summary: A collection of reference inference implementations for gpt-oss by OpenAI
Requires-Python: >=3.12
License-File: LICENSE
Requires-Dist: openai-harmony
Requires-Dist: tiktoken>=0.9.0
Requires-Dist: aiohttp>=3.12.14
Requires-Dist: chz>=0.3.0
Requires-Dist: docker>=7.1.0
Requires-Dist: fastapi>=0.116.1
Requires-Dist: html2text>=2025.4.15
Requires-Dist: lxml>=4.9.4
Requires-Dist: pydantic>=2.11.7
Requires-Dist: structlog>=25.4.0
Requires-Dist: tenacity>=9.1.2
Requires-Dist: uvicorn>=0.35.0
Requires-Dist: requests>=2.31.0
Requires-Dist: termcolor
Provides-Extra: triton
Requires-Dist: triton>=3.4; extra == "triton"
Requires-Dist: safetensors>=0.5.3; extra == "triton"
Requires-Dist: torch>=2.7.0; extra == "triton"
Provides-Extra: torch
Requires-Dist: safetensors>=0.5.3; extra == "torch"
Requires-Dist: torch>=2.7.0; extra == "torch"
Provides-Extra: metal
Requires-Dist: numpy; extra == "metal"
Requires-Dist: tqdm; extra == "metal"
Requires-Dist: safetensors; extra == "metal"
Requires-Dist: torch; extra == "metal"
Provides-Extra: test
Requires-Dist: pytest>=8.4.1; extra == "test"
Requires-Dist: httpx>=0.28.1; extra == "test"
Provides-Extra: eval
Requires-Dist: pandas; extra == "eval"
Requires-Dist: numpy; extra == "eval"
Requires-Dist: openai; extra == "eval"
Requires-Dist: jinja2; extra == "eval"
Requires-Dist: tqdm; extra == "eval"
Requires-Dist: blobfile; extra == "eval"
Dynamic: license-file
